cdist/__init__.py
cdist/argparse.py
cdist/autil.py
cdist/banner.py
cdist/config.py
cdist/configuration.py
cdist/emulator.py
cdist/flock.py
cdist/hostsource.py
cdist/info.py
cdist/install.py
cdist/integration.py
cdist/inventory.py
cdist/log.py
cdist/message.py
cdist/mputil.py
cdist/preos.py
cdist/shell.py
cdist/version.py
cdist/conf/README
cdist/conf/explorer/cpu_cores
cdist/conf/explorer/cpu_sockets
cdist/conf/explorer/disks
cdist/conf/explorer/hostname
cdist/conf/explorer/init
cdist/conf/explorer/interfaces
cdist/conf/explorer/is-freebsd-jail
cdist/conf/explorer/kernel_name
cdist/conf/explorer/lsb_codename
cdist/conf/explorer/lsb_description
cdist/conf/explorer/lsb_id
cdist/conf/explorer/lsb_release
cdist/conf/explorer/machine
cdist/conf/explorer/machine_type
cdist/conf/explorer/memory
cdist/conf/explorer/os
cdist/conf/explorer/os_release
cdist/conf/explorer/os_version
cdist/conf/explorer/runlevel
cdist/conf/manifest/sample-from-distribution
cdist/conf/type/__acl/gencode-remote
cdist/conf/type/__acl/man.rst
cdist/conf/type/__acl/manifest
cdist/conf/type/__acl/explorer/acl_is
cdist/conf/type/__acl/explorer/file_is
cdist/conf/type/__acl/explorer/getent
cdist/conf/type/__acl/parameter/boolean
cdist/conf/type/__acl/parameter/optional
cdist/conf/type/__acl/parameter/optional_multiple
cdist/conf/type/__apt_backports/man.rst
cdist/conf/type/__apt_backports/manifest
cdist/conf/type/__apt_backports/singleton
cdist/conf/type/__apt_backports/parameter/optional
cdist/conf/type/__apt_backports/parameter/default/state
cdist/conf/type/__apt_default_release/man.rst
cdist/conf/type/__apt_default_release/manifest
cdist/conf/type/__apt_default_release/singleton
cdist/conf/type/__apt_default_release/parameter/required
cdist/conf/type/__apt_key/gencode-remote
cdist/conf/type/__apt_key/man.rst
cdist/conf/type/__apt_key/manifest
cdist/conf/type/__apt_key/explorer/state
cdist/conf/type/__apt_key/parameter/boolean
cdist/conf/type/__apt_key/parameter/optional
cdist-7.0.0.dist-info/LICENSE
cdist-7.0.0.dist-info/METADATA
cdist-7.0.0.dist-info/WHEEL
cdist-7.0.0.dist-info/top_level.txt
cdist-7.0.0.dist-info/RECORD
